<?xml version="1.0" encoding="utf-8"?>
<Defs>

	<!-- Xenohumans - Anthromorphs. 2349467636. https://steamcommunity.com/sharedfiles/filedetails/?id=2349467636 -->
	
	<rjw.RaceGroupDef>
		<defName>Anthromorphs_A</defName>
		<raceNames>
			<li>ATK_Avianmorph</li>
		</raceNames>
		<anuses>
			<li>CloacalAnus</li>
		</anuses>
		<femaleBreasts>
			<li>FeaturelessChest</li>
		</femaleBreasts>
		<femaleGenitals>
			<li>CloacalVagina</li>
		</femaleGenitals>
		<maleBreasts>
			<li>FeaturelessChest</li>
		</maleBreasts>
		<maleGenitals>
			<li>CloacalPenis</li>
		</maleGenitals>
		<tags>
			<li>Feathers</li>
		</tags>
		<hasFertility>true</hasFertility>
		<hasPregnancy>true</hasPregnancy>
		<oviPregnancy>true</oviPregnancy>
		<ImplantEggs>false</ImplantEggs>
	</rjw.RaceGroupDef>
	
	<rjw.RaceGroupDef>
		<defName>Anthromorphs_B</defName>
		<raceNames>
			<li>ATK_Bovinemorph</li>
		</raceNames>
		<anuses>
			<li>GenericAnus</li>
		</anuses>
		<femaleBreasts>
			<li>UdderBreasts</li>
		</femaleBreasts>
		<femaleGenitals>
			<li>GenericVagina</li>
		</femaleGenitals>
		<maleBreasts>
		</maleBreasts>
		<maleGenitals>
			<li>BovinePenis</li>
		</maleGenitals>
		<tags>
			<li>Fur</li>
		</tags>
		<hasSingleGender>false</hasSingleGender>
		<hasSexNeed>true</hasSexNeed>
		<hasFertility>true</hasFertility>
		<hasPregnancy>true</hasPregnancy>
		<oviPregnancy>false</oviPregnancy>
		<ImplantEggs>false</ImplantEggs>
	</rjw.RaceGroupDef>
	
	<rjw.RaceGroupDef>
		<defName>Anthromorphs_C</defName>
		<raceNames>
			<li>ATK_Caninemorph</li>
		</raceNames>
		<anuses>
			<li>DogAnus</li>
		</anuses>
		<femaleBreasts>
			<li>Breasts</li>
		</femaleBreasts>
		<femaleGenitals>
			<li>DogVagina</li>
		</femaleGenitals>
		<maleBreasts>
			<li>Breasts</li>
		</maleBreasts>
		<maleGenitals>
			<li>DogPenis</li>
		</maleGenitals>
		<tags>
			<li>Fur</li>
		</tags>
		<hasSingleGender>false</hasSingleGender>
		<hasSexNeed>true</hasSexNeed>
		<hasFertility>true</hasFertility>
		<hasPregnancy>true</hasPregnancy>
		<oviPregnancy>false</oviPregnancy>
		<ImplantEggs>false</ImplantEggs>
	</rjw.RaceGroupDef>
	
	<rjw.RaceGroupDef>
		<defName>Anthromorphs_D</defName>
		<raceNames>
			<li>ATK_Dragomorph</li>
		</raceNames>
		<anuses>
			<li>CloacalAnus</li>
		</anuses>
		<femaleBreasts>
			<li>ScaleBreasts</li>
		</femaleBreasts>
		<femaleGenitals>
			<li>DragonVagina</li>
		</femaleGenitals>
		<maleBreasts>
			<li>ScaleBreasts</li>
		</maleBreasts>
		<maleGenitals>
			<li>DragonPenis</li>
		</maleGenitals>
		<tags>
			<li>Scale</li>
		</tags>
		<hasSingleGender>false</hasSingleGender>
		<hasSexNeed>true</hasSexNeed>
		<hasFertility>true</hasFertility>
		<hasPregnancy>true</hasPregnancy>
		<oviPregnancy>false</oviPregnancy>
		<ImplantEggs>false</ImplantEggs>
	</rjw.RaceGroupDef>
	
	<rjw.RaceGroupDef>
		<defName>Anthromorphs_E</defName>
		<raceNames>
			<li>ATK_Cervinemorph</li>
		</raceNames>
		<anuses>
			<li>CervineAnus</li>
		</anuses>
		<femaleBreasts>
			<li>UdderBreasts</li>
		</femaleBreasts>
		<femaleGenitals>
			<li>CervineVagina</li>
		</femaleGenitals>
		<maleBreasts>
			<li>Breasts</li>
		</maleBreasts>
		<maleGenitals>
			<li>BovinePenis</li>
		</maleGenitals>
		<tags>
			<li>Fur</li>
		</tags>
		<hasSingleGender>false</hasSingleGender>
		<hasSexNeed>true</hasSexNeed>
		<hasFertility>true</hasFertility>
		<hasPregnancy>true</hasPregnancy>
		<oviPregnancy>false</oviPregnancy>
		<ImplantEggs>false</ImplantEggs>
	</rjw.RaceGroupDef>
	
	<rjw.RaceGroupDef>
		<defName>Anthromorphs_F</defName>
		<raceNames>
			<li>ATK_Felinemorph</li>
		</raceNames>
		<anuses>
			<li>CatAnus</li>
		</anuses>
		<femaleBreasts>
			<li>Breasts</li>
		</femaleBreasts>
		<femaleGenitals>
			<li>CatVagina</li>
		</femaleGenitals>
		<maleBreasts>
			<li>Breasts</li>
		</maleBreasts>
		<maleGenitals>
			<li>CatPenis</li>
		</maleGenitals>
		<tags>
			<li>Fur</li>
		</tags>
		<hasSingleGender>false</hasSingleGender>
		<hasSexNeed>true</hasSexNeed>
		<hasFertility>true</hasFertility>
		<hasPregnancy>true</hasPregnancy>
		<oviPregnancy>false</oviPregnancy>
		<ImplantEggs>false</ImplantEggs>
	</rjw.RaceGroupDef>
	
	<rjw.RaceGroupDef>
		<defName>Anthromorphs_G</defName>
		<raceNames>
			<li>ATK_Gnollmorph</li>
		</raceNames>
		<anuses>
			<li>CatAnus</li>
		</anuses>
		<femaleBreasts>
			<li>Breasts</li>
		</femaleBreasts>
		<femaleGenitals>
			<li>DogPenis</li>
			<li>CatVagina</li>
		</femaleGenitals>
		<maleBreasts>
			<li>Breasts</li>
		</maleBreasts>
		<maleGenitals>
			<li>DogPenis</li>
		</maleGenitals>
		<tags>
			<li>Fur</li>
		</tags>
		<hasSingleGender>false</hasSingleGender>
		<hasSexNeed>true</hasSexNeed>
		<hasFertility>true</hasFertility>
		<hasPregnancy>true</hasPregnancy>
		<oviPregnancy>false</oviPregnancy>
		<ImplantEggs>false</ImplantEggs>
	</rjw.RaceGroupDef>
	
	<rjw.RaceGroupDef>
		<defName>Anthromorphs_H</defName>
		<raceNames>
			<li>ATK_Lagomorph</li>
		</raceNames>
		<anuses>
			<li>Petite_Anus</li>
		</anuses>
		<femaleBreasts>
			<li>Petite_Breasts</li>
		</femaleBreasts>
		<femaleGenitals>
			<li>Petite_Vagina</li>
		</femaleGenitals>
		<maleBreasts>
			<li>Breasts</li>
		</maleBreasts>
		<maleGenitals>
			<li>Petite_Penis</li>
		</maleGenitals>
		<tags>
			<li>Fur</li>
		</tags>
		<raceSexDrive>1.2</raceSexDrive>
		<hasSingleGender>false</hasSingleGender>
		<hasSexNeed>true</hasSexNeed>
		<hasFertility>true</hasFertility>
		<hasPregnancy>true</hasPregnancy>
		<oviPregnancy>false</oviPregnancy>
		<ImplantEggs>false</ImplantEggs>
	</rjw.RaceGroupDef>
	
	<rjw.RaceGroupDef>
		<defName>Anthromorphs_I</defName>
		<raceNames>
			<li>ATK_Vulpinemorph</li>
		</raceNames>
		<anuses>
			<li>DogAnus</li>
		</anuses>
		<femaleBreasts>
			<li>Breasts</li>
		</femaleBreasts>
		<femaleGenitals>
			<li>DogVagina</li>
		</femaleGenitals>
		<maleBreasts>
			<li>Breasts</li>
		</maleBreasts>
		<maleGenitals>
			<li>DogPenis</li>
		</maleGenitals>
		<tags>
			<li>Fur</li>
		</tags>
		<hasSingleGender>false</hasSingleGender>
		<hasSexNeed>true</hasSexNeed>
		<hasFertility>true</hasFertility>
		<hasPregnancy>true</hasPregnancy>
		<oviPregnancy>false</oviPregnancy>
		<ImplantEggs>false</ImplantEggs>
	</rjw.RaceGroupDef>
	
</Defs>